pinterest_scraper/__init__.py
pinterest_scraper/exceptions.py
pinterest_scraper/extractor.py
pinterest_scraper/scraper.py
tests/__init__.py
tests/test_extractor.py
tests/test_scraper.py
pinterest_scraper-0.1.0.dist-info/METADATA
pinterest_scraper-0.1.0.dist-info/WHEEL
pinterest_scraper-0.1.0.dist-info/top_level.txt
pinterest_scraper-0.1.0.dist-info/RECORD
